pytest_tinybird/__init__.py
pytest_tinybird/plugin.py
pytest_tinybird/tinybird.py
pytest_tinybird-0.5.0.dist-info/licenses/LICENSE
pytest_tinybird-0.5.0.dist-info/METADATA
pytest_tinybird-0.5.0.dist-info/WHEEL
pytest_tinybird-0.5.0.dist-info/entry_points.txt
pytest_tinybird-0.5.0.dist-info/top_level.txt
pytest_tinybird-0.5.0.dist-info/RECORD
