Metadata-Version: 2.4
Name: pytest-tinybird
Version: 0.5.0
Summary: A pytest plugin to report test results to tinybird
Home-page: https://github.com/jlmadurga/pytest-tinybird
Author: jlmadurga
Author-email: jlmadurga@gmail.com
License: MIT
Classifier: Development Status :: 4 - Beta
Classifier: Programming Language :: Python
Classifier: Programming Language :: Python :: 3
Classifier: Programming Language :: Python :: 3.8
Classifier: Programming Language :: Python :: 3.9
Classifier: Programming Language :: Python :: 3.10
Classifier: Programming Language :: Python :: 3.11
Classifier: Framework :: Pytest
License-File: LICENSE
Requires-Dist: pytest>=3.8.0
Requires-Dist: requests>=2.28.1
Dynamic: author
Dynamic: author-email
Dynamic: classifier
Dynamic: description
Dynamic: description-content-type
Dynamic: home-page
Dynamic: license
Dynamic: license-file
Dynamic: requires-dist
Dynamic: summary
